rpi_ws281x_light_show/__init__.py
rpi_ws281x_light_show/matrix/__init__.py
rpi_ws281x_light_show/matrix/matrix.py
rpi_ws281x_light_show/matrix/frame/__init__.py
rpi_ws281x_light_show/matrix/frame/frame.py
rpi_ws281x_light_show/matrix/frame/pixel/__init__.py
rpi_ws281x_light_show/matrix/frame/pixel/pixel.py
rpi_ws281x_light_show/matrix/frame/pixel/color/__init__.py
rpi_ws281x_light_show/matrix/frame/pixel/color/color.py
rpi_ws281x_light_show-0.1.7.data/scripts/rpi_ws281x_light_show
rpi_ws281x_light_show-0.1.7.dist-info/METADATA
rpi_ws281x_light_show-0.1.7.dist-info/WHEEL
rpi_ws281x_light_show-0.1.7.dist-info/top_level.txt
rpi_ws281x_light_show-0.1.7.dist-info/RECORD
